django_test_data_migrations/__init__.py
django_test_data_migrations/unittest.py
django_test_data_migrations/utils.py
django_test_data_migrations-0.1.2.dist-info/LICENSE
django_test_data_migrations-0.1.2.dist-info/WHEEL
django_test_data_migrations-0.1.2.dist-info/METADATA
django_test_data_migrations-0.1.2.dist-info/RECORD
