Metadata-Version: 2.1
Name: django-test-data-migrations
Version: 0.1.2
Summary: Test utilities for easily testing Django data migrations
Home-page: https://github.com/imranariffin/django-test-data-migrations
License: MIT
Keywords: django,django-test,django-migration,django-migrations,django-data-migration-test,django-data-migration-tests,django-orm,migration,migrations,data-migration,data-migrations,orm,sql,tests,test
Author: Imran Ariffin
Author-email: ariffin.imran@gmail.com
Requires-Python: >=3.6,<4.0
Classifier: License :: OSI Approved :: MIT License
Classifier: Programming Language :: Python :: 3
Classifier: Programming Language :: Python :: 3.6
Classifier: Programming Language :: Python :: 3.7
Classifier: Programming Language :: Python :: 3.8
Classifier: Programming Language :: Python :: 3.9
Project-URL: Repository, https://github.com/imranariffin/django-test-data-migrations
